imagesorcery_mcp/__init__.py
imagesorcery_mcp/__main__.py
imagesorcery_mcp/config.py
imagesorcery_mcp/logging_config.py
imagesorcery_mcp/server.py
imagesorcery_mcp/telemetry_amplitude.py
imagesorcery_mcp/telemetry_keys.py
imagesorcery_mcp/telemetry_posthog.py
imagesorcery_mcp/middlewares/telemetry.py
imagesorcery_mcp/middlewares/validation.py
imagesorcery_mcp/prompts/__init__.py
imagesorcery_mcp/prompts/remove_background.py
imagesorcery_mcp/resources/__init__.py
imagesorcery_mcp/resources/models.py
imagesorcery_mcp/scripts/__init__.py
imagesorcery_mcp/scripts/clear_telemetry_keys.py
imagesorcery_mcp/scripts/create_model_descriptions.py
imagesorcery_mcp/scripts/download_clip.py
imagesorcery_mcp/scripts/download_models.py
imagesorcery_mcp/scripts/populate_telemetry_keys.py
imagesorcery_mcp/scripts/post_install.py
imagesorcery_mcp/tools/__init__.py
imagesorcery_mcp/tools/blur.py
imagesorcery_mcp/tools/change_color.py
imagesorcery_mcp/tools/config.py
imagesorcery_mcp/tools/crop.py
imagesorcery_mcp/tools/detect.py
imagesorcery_mcp/tools/draw_arrows.py
imagesorcery_mcp/tools/draw_circle.py
imagesorcery_mcp/tools/draw_lines.py
imagesorcery_mcp/tools/draw_rectangle.py
imagesorcery_mcp/tools/draw_text.py
imagesorcery_mcp/tools/fill.py
imagesorcery_mcp/tools/find.py
imagesorcery_mcp/tools/metainfo.py
imagesorcery_mcp/tools/ocr.py
imagesorcery_mcp/tools/overlay.py
imagesorcery_mcp/tools/resize.py
imagesorcery_mcp/tools/rotate.py
mseep_imagesorcery_mcp-0.11.5.dist-info/licenses/LICENSE
mseep_imagesorcery_mcp-0.11.5.dist-info/METADATA
mseep_imagesorcery_mcp-0.11.5.dist-info/WHEEL
mseep_imagesorcery_mcp-0.11.5.dist-info/entry_points.txt
mseep_imagesorcery_mcp-0.11.5.dist-info/top_level.txt
mseep_imagesorcery_mcp-0.11.5.dist-info/RECORD
